{
  "version": "3.3.10",
  "flags": {},
  "shapes": [
    {
      "label": "person",
      "score": 0.8405565619468689,
      "points": [
        [
          621.0,
          1162.0
        ],
        [
          622.0,
          1170.0
        ],
        [
          625.0,
          1176.0
        ],
        [
          629.0,
          1178.0
        ],
        [
          656.0,
          1177.0
        ],
        [
          662.0,
          1173.0
        ],
        [
          683.0,
          1173.0
        ],
        [
          689.0,
          1179.0
        ],
        [
          692.0,
          1191.0
        ],
        [
          696.0,
          1194.0
        ],
        [
          728.0,
          1194.0
        ],
        [
          743.0,
          1189.0
        ],
        [
          747.0,
          1180.0
        ],
        [
          752.0,
          1184.0
        ],
        [
          766.0,
          1189.0
        ],
        [
          780.0,
          1188.0
        ],
        [
          803.0,
          1190.0
        ],
        [
          823.0,
          1203.0
        ],
        [
          833.0,
          1207.0
        ],
        [
          845.0,
          1218.0
        ],
        [
          862.0,
          1218.0
        ],
        [
          882.0,
          1226.0
        ],
        [
          894.0,
          1228.0
        ],
        [
          901.0,
          1236.0
        ],
        [
          917.0,
          1234.0
        ],
        [
          924.0,
          1240.0
        ],
        [
          940.0,
          1241.0
        ],
        [
          958.0,
          1245.0
        ],
        [
          965.0,
          1244.0
        ],
        [
          969.0,
          1246.0
        ],
        [
          987.0,
          1246.0
        ],
        [
          1010.0,
          1243.0
        ],
        [
          1027.0,
          1250.0
        ],
        [
          1039.0,
          1251.0
        ],
        [
          1051.0,
          1255.0
        ],
        [
          1074.0,
          1255.0
        ],
        [
          1079.0,
          1253.0
        ],
        [
          1079.0,
          1236.0
        ],
        [
          1059.0,
          1234.0
        ],
        [
          1055.0,
          1231.0
        ],
        [
          1052.0,
          1234.0
        ],
        [
          1040.0,
          1231.0
        ],
        [
          1033.0,
          1224.0
        ],
        [
          1038.0,
          1217.0
        ],
        [
          1048.0,
          1213.0
        ],
        [
          1051.0,
          1209.0
        ],
        [
          1055.0,
          1197.0
        ],
        [
          1054.0,
          1187.0
        ],
        [
          1042.0,
          1174.0
        ],
        [
          1026.0,
          1174.0
        ],
        [
          1021.0,
          1163.0
        ],
        [
          1018.0,
          1163.0
        ],
        [
          1017.0,
          1170.0
        ],
        [
          1014.0,
          1172.0
        ],
        [
          1006.0,
          1164.0
        ],
        [
          1003.0,
          1171.0
        ],
        [
          981.0,
          1170.0
        ],
        [
          972.0,
          1177.0
        ],
        [
          952.0,
          1179.0
        ],
        [
          945.0,
          1185.0
        ],
        [
          934.0,
          1187.0
        ],
        [
          928.0,
          1191.0
        ],
        [
          895.0,
          1192.0
        ],
        [
          893.0,
          1187.0
        ],
        [
          898.0,
          1177.0
        ],
        [
          910.0,
          1177.0
        ],
        [
          914.0,
          1168.0
        ],
        [
          920.0,
          1168.0
        ],
        [
          920.0,
          1163.0
        ],
        [
          918.0,
          1161.0
        ],
        [
          902.0,
          1162.0
        ],
        [
          894.0,
          1159.0
        ],
        [
          871.0,
          1175.0
        ],
        [
          846.0,
          1175.0
        ],
        [
          823.0,
          1170.0
        ],
        [
          808.0,
          1170.0
        ],
        [
          800.0,
          1167.0
        ],
        [
          779.0,
          1165.0
        ],
        [
          742.0,
          1143.0
        ],
        [
          708.0,
          1133.0
        ],
        [
          699.0,
          1124.0
        ],
        [
          685.0,
          1123.0
        ],
        [
          666.0,
          1116.0
        ],
        [
          639.0,
          1113.0
        ],
        [
          634.0,
          1116.0
        ],
        [
          630.0,
          1129.0
        ],
        [
          632.0,
          1151.0
        ],
        [
          625.0,
          1156.0
        ]
      ],
      "group_id": null,
      "description": null,
      "difficult": false,
      "shape_type": "polygon",
      "flags": null,
      "attributes": {},
      "kie_linking": []
    },
    {
      "label": "person",
      "score": 0.8405565619468689,
      "points": [
        [
          619.85205078125,
          1112.2042236328125
        ],
        [
          1084.672607421875,
          1112.2042236328125
        ],
        [
          1084.672607421875,
          1291.044921875
        ],
        [
          619.85205078125,
          1291.044921875
        ]
      ],
      "group_id": null,
      "description": null,
      "difficult": false,
      "shape_type": "rectangle",
      "flags": null,
      "attributes": {},
      "kie_linking": []
    },
    {
      "label": "person",
      "score": 0.8324155211448669,
      "points": [
        [
          74.0,
          1000.0
        ],
        [
          72.0,
          1001.0
        ],
        [
          68.0,
          1006.0
        ],
        [
          62.0,
          1009.0
        ],
        [
          59.0,
          1012.0
        ],
        [
          56.0,
          1013.0
        ],
        [
          49.0,
          1019.0
        ],
        [
          45.0,
          1021.0
        ],
        [
          40.0,
          1027.0
        ],
        [
          40.0,
          1029.0
        ],
        [
          36.0,
          1036.0
        ],
        [
          36.0,
          1038.0
        ],
        [
          34.0,
          1042.0
        ],
        [
          34.0,
          1046.0
        ],
        [
          33.0,
          1047.0
        ],
        [
          33.0,
          1054.0
        ],
        [
          32.0,
          1055.0
        ],
        [
          32.0,
          1058.0
        ],
        [
          33.0,
          1059.0
        ],
        [
          33.0,
          1067.0
        ],
        [
          32.0,
          1068.0
        ],
        [
          32.0,
          1074.0
        ],
        [
          33.0,
          1075.0
        ],
        [
          33.0,
          1090.0
        ],
        [
          34.0,
          1092.0
        ],
        [
          35.0,
          1092.0
        ],
        [
          39.0,
          1096.0
        ],
        [
          47.0,
          1098.0
        ],
        [
          55.0,
          1105.0
        ],
        [
          57.0,
          1105.0
        ],
        [
          61.0,
          1108.0
        ],
        [
          69.0,
          1112.0
        ],
        [
          71.0,
          1112.0
        ],
        [
          72.0,
          1113.0
        ],
        [
          76.0,
          1114.0
        ],
        [
          83.0,
          1120.0
        ],
        [
          89.0,
          1133.0
        ],
        [
          101.0,
          1149.0
        ],
        [
          102.0,
          1152.0
        ],
        [
          104.0,
          1154.0
        ],
        [
          110.0,
          1166.0
        ],
        [
          110.0,
          1168.0
        ],
        [
          112.0,
          1170.0
        ],
        [
          114.0,
          1171.0
        ],
        [
          141.0,
          1171.0
        ],
        [
          142.0,
          1170.0
        ],
        [
          147.0,
          1170.0
        ],
        [
          148.0,
          1169.0
        ],
        [
          147.0,
          1169.0
        ],
        [
          145.0,
          1167.0
        ],
        [
          144.0,
          1163.0
        ],
        [
          141.0,
          1160.0
        ],
        [
          137.0,
          1152.0
        ],
        [
          137.0,
          1150.0
        ],
        [
          135.0,
          1148.0
        ],
        [
          132.0,
          1142.0
        ],
        [
          129.0,
          1139.0
        ],
        [
          129.0,
          1138.0
        ],
        [
          125.0,
          1133.0
        ],
        [
          124.0,
          1130.0
        ],
        [
          120.0,
          1125.0
        ],
        [
          119.0,
          1122.0
        ],
        [
          115.0,
          1117.0
        ],
        [
          115.0,
          1115.0
        ],
        [
          111.0,
          1108.0
        ],
        [
          111.0,
          1105.0
        ],
        [
          109.0,
          1103.0
        ],
        [
          121.0,
          1097.0
        ],
        [
          122.0,
          1093.0
        ],
        [
          123.0,
          1092.0
        ],
        [
          123.0,
          1083.0
        ],
        [
          122.0,
          1082.0
        ],
        [
          121.0,
          1078.0
        ],
        [
          119.0,
          1076.0
        ],
        [
          116.0,
          1075.0
        ],
        [
          107.0,
          1065.0
        ],
        [
          102.0,
          1056.0
        ],
        [
          102.0,
          1052.0
        ],
        [
          101.0,
          1051.0
        ],
        [
          101.0,
          1030.0
        ],
        [
          102.0,
          1029.0
        ],
        [
          103.0,
          1021.0
        ],
        [
          106.0,
          1017.0
        ],
        [
          107.0,
          1013.0
        ],
        [
          109.0,
          1010.0
        ],
        [
          109.0,
          1006.0
        ],
        [
          108.0,
          1005.0
        ],
        [
          108.0,
          1003.0
        ],
        [
          106.0,
          1001.0
        ],
        [
          103.0,
          1001.0
        ],
        [
          102.0,
          1000.0
        ],
        [
          94.0,
          1000.0
        ],
        [
          93.0,
          999.0
        ],
        [
          78.0,
          999.0
        ],
        [
          77.0,
          1000.0
        ]
      ],
      "group_id": null,
      "description": null,
      "difficult": false,
      "shape_type": "polygon",
      "flags": null,
      "attributes": {},
      "kie_linking": []
    },
    {
      "label": "person",
      "score": 0.8324155211448669,
      "points": [
        [
          31.994672775268555,
          998.5877685546875
        ],
        [
          147.63307189941406,
          998.5877685546875
        ],
        [
          147.63307189941406,
          1173.172607421875
        ],
        [
          31.994672775268555,
          1173.172607421875
        ]
      ],
      "group_id": null,
      "description": null,
      "difficult": false,
      "shape_type": "rectangle",
      "flags": null,
      "attributes": {},
      "kie_linking": []
    },
    {
      "label": "person",
      "score": 0.8493891358375549,
      "points": [
        [
          740.0,
          1093.0
        ],
        [
          740.0,
          1103.0
        ],
        [
          744.0,
          1107.0
        ],
        [
          744.0,
          1108.0
        ],
        [
          747.0,
          1108.0
        ],
        [
          751.0,
          1110.0
        ],
        [
          755.0,
          1109.0
        ],
        [
          756.0,
          1110.0
        ],
        [
          767.0,
          1110.0
        ],
        [
          768.0,
          1111.0
        ],
        [
          771.0,
          1111.0
        ],
        [
          775.0,
          1113.0
        ],
        [
          777.0,
          1115.0
        ],
        [
          782.0,
          1117.0
        ],
        [
          793.0,
          1128.0
        ],
        [
          799.0,
          1131.0
        ],
        [
          801.0,
          1131.0
        ],
        [
          805.0,
          1133.0
        ],
        [
          807.0,
          1135.0
        ],
        [
          811.0,
          1136.0
        ],
        [
          815.0,
          1139.0
        ],
        [
          823.0,
          1143.0
        ],
        [
          825.0,
          1143.0
        ],
        [
          829.0,
          1145.0
        ],
        [
          837.0,
          1146.0
        ],
        [
          838.0,
          1147.0
        ],
        [
          849.0,
          1147.0
        ],
        [
          850.0,
          1148.0
        ],
        [
          855.0,
          1148.0
        ],
        [
          856.0,
          1149.0
        ],
        [
          860.0,
          1148.0
        ],
        [
          863.0,
          1150.0
        ],
        [
          869.0,
          1150.0
        ],
        [
          870.0,
          1151.0
        ],
        [
          877.0,
          1151.0
        ],
        [
          878.0,
          1150.0
        ],
        [
          881.0,
          1150.0
        ],
        [
          882.0,
          1151.0
        ],
        [
          891.0,
          1151.0
        ],
        [
          892.0,
          1150.0
        ],
        [
          895.0,
          1150.0
        ],
        [
          907.0,
          1144.0
        ],
        [
          919.0,
          1143.0
        ],
        [
          922.0,
          1141.0
        ],
        [
          928.0,
          1141.0
        ],
        [
          930.0,
          1140.0
        ],
        [
          935.0,
          1135.0
        ],
        [
          942.0,
          1132.0
        ],
        [
          946.0,
          1132.0
        ],
        [
          947.0,
          1131.0
        ],
        [
          970.0,
          1131.0
        ],
        [
          971.0,
          1130.0
        ],
        [
          973.0,
          1130.0
        ],
        [
          973.0,
          1129.0
        ],
        [
          972.0,
          1129.0
        ],
        [
          969.0,
          1126.0
        ],
        [
          967.0,
          1126.0
        ],
        [
          964.0,
          1123.0
        ],
        [
          960.0,
          1123.0
        ],
        [
          959.0,
          1122.0
        ],
        [
          953.0,
          1122.0
        ],
        [
          952.0,
          1121.0
        ],
        [
          947.0,
          1121.0
        ],
        [
          943.0,
          1119.0
        ],
        [
          934.0,
          1119.0
        ],
        [
          933.0,
          1118.0
        ],
        [
          898.0,
          1118.0
        ],
        [
          897.0,
          1119.0
        ],
        [
          893.0,
          1119.0
        ],
        [
          892.0,
          1120.0
        ],
        [
          885.0,
          1120.0
        ],
        [
          884.0,
          1121.0
        ],
        [
          880.0,
          1121.0
        ],
        [
          879.0,
          1122.0
        ],
        [
          873.0,
          1122.0
        ],
        [
          872.0,
          1123.0
        ],
        [
          868.0,
          1123.0
        ],
        [
          865.0,
          1125.0
        ],
        [
          862.0,
          1125.0
        ],
        [
          861.0,
          1126.0
        ],
        [
          857.0,
          1125.0
        ],
        [
          850.0,
          1120.0
        ],
        [
          847.0,
          1120.0
        ],
        [
          846.0,
          1119.0
        ],
        [
          841.0,
          1119.0
        ],
        [
          840.0,
          1120.0
        ],
        [
          837.0,
          1120.0
        ],
        [
          836.0,
          1121.0
        ],
        [
          825.0,
          1121.0
        ],
        [
          824.0,
          1120.0
        ],
        [
          820.0,
          1120.0
        ],
        [
          819.0,
          1119.0
        ],
        [
          814.0,
          1118.0
        ],
        [
          812.0,
          1116.0
        ],
        [
          806.0,
          1115.0
        ],
        [
          800.0,
          1110.0
        ],
        [
          797.0,
          1109.0
        ],
        [
          790.0,
          1103.0
        ],
        [
          785.0,
          1101.0
        ],
        [
          780.0,
          1096.0
        ],
        [
          766.0,
          1089.0
        ],
        [
          759.0,
          1089.0
        ],
        [
          758.0,
          1088.0
        ],
        [
          745.0,
          1088.0
        ],
        [
          743.0,
          1089.0
        ]
      ],
      "group_id": null,
      "description": null,
      "difficult": false,
      "shape_type": "polygon",
      "flags": null,
      "attributes": {},
      "kie_linking": []
    },
    {
      "label": "person",
      "score": 0.8493891358375549,
      "points": [
        [
          737.0284423828125,
          1087.8048095703125
        ],
        [
          975.1181030273438,
          1087.8048095703125
        ],
        [
          975.1181030273438,
          1151.8470458984375
        ],
        [
          737.0284423828125,
          1151.8470458984375
        ]
      ],
      "group_id": null,
      "description": null,
      "difficult": false,
      "shape_type": "rectangle",
      "flags": null,
      "attributes": {},
      "kie_linking": []
    },
    {
      "label": "person",
      "score": 0.9445844292640686,
      "points": [
        [
          293.0,
          1158.0
        ],
        [
          292.0,
          1195.0
        ],
        [
          298.0,
          1229.0
        ],
        [
          349.0,
          1324.0
        ],
        [
          366.0,
          1345.0
        ],
        [
          376.0,
          1364.0
        ],
        [
          393.0,
          1376.0
        ],
        [
          406.0,
          1376.0
        ],
        [
          416.0,
          1372.0
        ],
        [
          481.0,
          1361.0
        ],
        [
          506.0,
          1350.0
        ],
        [
          541.0,
          1327.0
        ],
        [
          567.0,
          1321.0
        ],
        [
          581.0,
          1313.0
        ],
        [
          665.0,
          1303.0
        ],
        [
          673.0,
          1298.0
        ],
        [
          688.0,
          1297.0
        ],
        [
          714.0,
          1288.0
        ],
        [
          733.0,
          1285.0
        ],
        [
          740.0,
          1279.0
        ],
        [
          770.0,
          1268.0
        ],
        [
          788.0,
          1283.0
        ],
        [
          820.0,
          1289.0
        ],
        [
          823.0,
          1283.0
        ],
        [
          822.0,
          1276.0
        ],
        [
          831.0,
          1267.0
        ],
        [
          859.0,
          1266.0
        ],
        [
          865.0,
          1261.0
        ],
        [
          878.0,
          1259.0
        ],
        [
          916.0,
          1269.0
        ],
        [
          930.0,
          1268.0
        ],
        [
          959.0,
          1276.0
        ],
        [
          984.0,
          1291.0
        ],
        [
          1009.0,
          1299.0
        ],
        [
          1026.0,
          1299.0
        ],
        [
          1032.0,
          1296.0
        ],
        [
          1032.0,
          1290.0
        ],
        [
          1024.0,
          1282.0
        ],
        [
          973.0,
          1247.0
        ],
        [
          945.0,
          1244.0
        ],
        [
          921.0,
          1233.0
        ],
        [
          869.0,
          1224.0
        ],
        [
          862.0,
          1219.0
        ],
        [
          844.0,
          1218.0
        ],
        [
          836.0,
          1210.0
        ],
        [
          830.0,
          1209.0
        ],
        [
          822.0,
          1201.0
        ],
        [
          804.0,
          1191.0
        ],
        [
          764.0,
          1188.0
        ],
        [
          748.0,
          1183.0
        ],
        [
          736.0,
          1185.0
        ],
        [
          733.0,
          1182.0
        ],
        [
          730.0,
          1183.0
        ],
        [
          734.0,
          1189.0
        ],
        [
          721.0,
          1196.0
        ],
        [
          685.0,
          1199.0
        ],
        [
          657.0,
          1205.0
        ],
        [
          627.0,
          1216.0
        ],
        [
          594.0,
          1238.0
        ],
        [
          575.0,
          1238.0
        ],
        [
          563.0,
          1231.0
        ],
        [
          554.0,
          1230.0
        ],
        [
          530.0,
          1233.0
        ],
        [
          513.0,
          1242.0
        ],
        [
          498.0,
          1255.0
        ],
        [
          480.0,
          1262.0
        ],
        [
          463.0,
          1273.0
        ],
        [
          444.0,
          1289.0
        ],
        [
          436.0,
          1290.0
        ],
        [
          425.0,
          1283.0
        ],
        [
          416.0,
          1258.0
        ],
        [
          371.0,
          1214.0
        ],
        [
          368.0,
          1206.0
        ],
        [
          371.0,
          1197.0
        ],
        [
          369.0,
          1183.0
        ],
        [
          338.0,
          1153.0
        ],
        [
          317.0,
          1140.0
        ],
        [
          305.0,
          1139.0
        ],
        [
          299.0,
          1142.0
        ]
      ],
      "group_id": null,
      "description": null,
      "difficult": false,
      "shape_type": "polygon",
      "flags": null,
      "attributes": {},
      "kie_linking": []
    },
    {
      "label": "person",
      "score": 0.9445844292640686,
      "points": [
        [
          290.0065002441406,
          1136.472412109375
        ],
        [
          1033.6326904296875,
          1136.472412109375
        ],
        [
          1033.6326904296875,
          1381.8701171875
        ],
        [
          290.0065002441406,
          1381.8701171875
        ]
      ],
      "group_id": null,
      "description": null,
      "difficult": false,
      "shape_type": "rectangle",
      "flags": null,
      "attributes": {},
      "kie_linking": []
    }
  ],
  "imagePath": "frame_00434.jpg",
  "imageData": null,
  "imageHeight": 1920,
  "imageWidth": 1080,
  "description": ""
}