{
  "version": "3.3.10",
  "flags": {},
  "shapes": [
    {
      "label": "person",
      "score": 0.9003462195396423,
      "points": [
        [
          749.0,
          1096.0
        ],
        [
          748.0,
          1109.0
        ],
        [
          750.0,
          1116.0
        ],
        [
          756.0,
          1125.0
        ],
        [
          768.0,
          1126.0
        ],
        [
          787.0,
          1123.0
        ],
        [
          797.0,
          1119.0
        ],
        [
          816.0,
          1118.0
        ],
        [
          856.0,
          1131.0
        ],
        [
          863.0,
          1136.0
        ],
        [
          888.0,
          1149.0
        ],
        [
          894.0,
          1157.0
        ],
        [
          894.0,
          1163.0
        ],
        [
          896.0,
          1161.0
        ],
        [
          904.0,
          1162.0
        ],
        [
          905.0,
          1163.0
        ],
        [
          901.0,
          1176.0
        ],
        [
          904.0,
          1171.0
        ],
        [
          916.0,
          1174.0
        ],
        [
          921.0,
          1172.0
        ],
        [
          928.0,
          1175.0
        ],
        [
          929.0,
          1177.0
        ],
        [
          927.0,
          1179.0
        ],
        [
          918.0,
          1180.0
        ],
        [
          918.0,
          1183.0
        ],
        [
          923.0,
          1190.0
        ],
        [
          926.0,
          1191.0
        ],
        [
          930.0,
          1196.0
        ],
        [
          937.0,
          1198.0
        ],
        [
          944.0,
          1203.0
        ],
        [
          954.0,
          1206.0
        ],
        [
          958.0,
          1210.0
        ],
        [
          962.0,
          1210.0
        ],
        [
          974.0,
          1216.0
        ],
        [
          986.0,
          1216.0
        ],
        [
          993.0,
          1213.0
        ],
        [
          1012.0,
          1209.0
        ],
        [
          1026.0,
          1203.0
        ],
        [
          1037.0,
          1194.0
        ],
        [
          1043.0,
          1192.0
        ],
        [
          1065.0,
          1202.0
        ],
        [
          1069.0,
          1203.0
        ],
        [
          1079.0,
          1202.0
        ],
        [
          1079.0,
          1142.0
        ],
        [
          1064.0,
          1141.0
        ],
        [
          1051.0,
          1138.0
        ],
        [
          1048.0,
          1139.0
        ],
        [
          1047.0,
          1138.0
        ],
        [
          1038.0,
          1138.0
        ],
        [
          1030.0,
          1140.0
        ],
        [
          1011.0,
          1127.0
        ],
        [
          1000.0,
          1122.0
        ],
        [
          974.0,
          1123.0
        ],
        [
          965.0,
          1125.0
        ],
        [
          964.0,
          1124.0
        ],
        [
          950.0,
          1124.0
        ],
        [
          937.0,
          1121.0
        ],
        [
          917.0,
          1121.0
        ],
        [
          881.0,
          1105.0
        ],
        [
          872.0,
          1103.0
        ],
        [
          847.0,
          1101.0
        ],
        [
          842.0,
          1099.0
        ],
        [
          835.0,
          1099.0
        ],
        [
          826.0,
          1090.0
        ],
        [
          820.0,
          1088.0
        ],
        [
          810.0,
          1088.0
        ],
        [
          802.0,
          1091.0
        ],
        [
          758.0,
          1090.0
        ],
        [
          752.0,
          1092.0
        ]
      ],
      "group_id": null,
      "description": null,
      "difficult": false,
      "shape_type": "polygon",
      "flags": null,
      "attributes": {},
      "kie_linking": []
    },
    {
      "label": "person",
      "score": 0.9003462195396423,
      "points": [
        [
          747.6476440429688,
          1086.2333984375
        ],
        [
          1075.1519775390625,
          1086.2333984375
        ],
        [
          1075.1519775390625,
          1215.8212890625
        ],
        [
          747.6476440429688,
          1215.8212890625
        ]
      ],
      "group_id": null,
      "description": null,
      "difficult": false,
      "shape_type": "rectangle",
      "flags": null,
      "attributes": {},
      "kie_linking": []
    },
    {
      "label": "person",
      "score": 0.9359362125396729,
      "points": [
        [
          0.0,
          1116.0
        ],
        [
          0.0,
          1163.0
        ],
        [
          13.0,
          1168.0
        ],
        [
          21.0,
          1176.0
        ],
        [
          24.0,
          1187.0
        ],
        [
          21.0,
          1192.0
        ],
        [
          8.0,
          1188.0
        ],
        [
          0.0,
          1190.0
        ],
        [
          0.0,
          1222.0
        ],
        [
          11.0,
          1228.0
        ],
        [
          72.0,
          1280.0
        ],
        [
          95.0,
          1292.0
        ],
        [
          114.0,
          1298.0
        ],
        [
          135.0,
          1295.0
        ],
        [
          152.0,
          1276.0
        ],
        [
          153.0,
          1212.0
        ],
        [
          159.0,
          1188.0
        ],
        [
          159.0,
          1176.0
        ],
        [
          165.0,
          1171.0
        ],
        [
          204.0,
          1197.0
        ],
        [
          230.0,
          1209.0
        ],
        [
          271.0,
          1217.0
        ],
        [
          323.0,
          1216.0
        ],
        [
          326.0,
          1220.0
        ],
        [
          329.0,
          1245.0
        ],
        [
          344.0,
          1275.0
        ],
        [
          364.0,
          1299.0
        ],
        [
          376.0,
          1307.0
        ],
        [
          383.0,
          1307.0
        ],
        [
          397.0,
          1299.0
        ],
        [
          478.0,
          1236.0
        ],
        [
          493.0,
          1245.0
        ],
        [
          512.0,
          1244.0
        ],
        [
          525.0,
          1231.0
        ],
        [
          535.0,
          1210.0
        ],
        [
          557.0,
          1190.0
        ],
        [
          551.0,
          1184.0
        ],
        [
          511.0,
          1199.0
        ],
        [
          496.0,
          1200.0
        ],
        [
          483.0,
          1190.0
        ],
        [
          486.0,
          1184.0
        ],
        [
          486.0,
          1169.0
        ],
        [
          478.0,
          1163.0
        ],
        [
          471.0,
          1170.0
        ],
        [
          476.0,
          1175.0
        ],
        [
          474.0,
          1189.0
        ],
        [
          481.0,
          1192.0
        ],
        [
          476.0,
          1203.0
        ],
        [
          466.0,
          1211.0
        ],
        [
          462.0,
          1210.0
        ],
        [
          445.0,
          1230.0
        ],
        [
          435.0,
          1232.0
        ],
        [
          421.0,
          1244.0
        ],
        [
          404.0,
          1244.0
        ],
        [
          391.0,
          1250.0
        ],
        [
          387.0,
          1240.0
        ],
        [
          393.0,
          1237.0
        ],
        [
          401.0,
          1239.0
        ],
        [
          408.0,
          1231.0
        ],
        [
          411.0,
          1202.0
        ],
        [
          402.0,
          1189.0
        ],
        [
          398.0,
          1177.0
        ],
        [
          399.0,
          1148.0
        ],
        [
          387.0,
          1135.0
        ],
        [
          377.0,
          1129.0
        ],
        [
          359.0,
          1123.0
        ],
        [
          323.0,
          1125.0
        ],
        [
          296.0,
          1120.0
        ],
        [
          215.0,
          1090.0
        ],
        [
          195.0,
          1089.0
        ],
        [
          148.0,
          1078.0
        ],
        [
          130.0,
          1077.0
        ],
        [
          106.0,
          1080.0
        ],
        [
          91.0,
          1087.0
        ],
        [
          80.0,
          1098.0
        ],
        [
          61.0,
          1108.0
        ],
        [
          55.0,
          1116.0
        ],
        [
          50.0,
          1145.0
        ],
        [
          37.0,
          1133.0
        ],
        [
          28.0,
          1116.0
        ],
        [
          23.0,
          1112.0
        ],
        [
          9.0,
          1110.0
        ]
      ],
      "group_id": null,
      "description": null,
      "difficult": false,
      "shape_type": "polygon",
      "flags": null,
      "attributes": {},
      "kie_linking": []
    },
    {
      "label": "person",
      "score": 0.9359362125396729,
      "points": [
        [
          -3.005737066268921,
          1079.2503662109375
        ],
        [
          557.67578125,
          1079.2503662109375
        ],
        [
          557.67578125,
          1306.97119140625
        ],
        [
          -3.005737066268921,
          1306.97119140625
        ]
      ],
      "group_id": null,
      "description": null,
      "difficult": false,
      "shape_type": "rectangle",
      "flags": null,
      "attributes": {},
      "kie_linking": []
    },
    {
      "label": "person",
      "score": 0.8443922996520996,
      "points": [
        [
          421.0,
          768.0
        ],
        [
          420.0,
          769.0
        ],
        [
          418.0,
          769.0
        ],
        [
          414.0,
          773.0
        ],
        [
          414.0,
          777.0
        ],
        [
          413.0,
          778.0
        ],
        [
          413.0,
          786.0
        ],
        [
          412.0,
          787.0
        ],
        [
          412.0,
          790.0
        ],
        [
          410.0,
          792.0
        ],
        [
          410.0,
          793.0
        ],
        [
          405.0,
          798.0
        ],
        [
          405.0,
          799.0
        ],
        [
          404.0,
          800.0
        ],
        [
          404.0,
          801.0
        ],
        [
          403.0,
          802.0
        ],
        [
          403.0,
          812.0
        ],
        [
          404.0,
          813.0
        ],
        [
          404.0,
          817.0
        ],
        [
          405.0,
          818.0
        ],
        [
          405.0,
          820.0
        ],
        [
          406.0,
          821.0
        ],
        [
          406.0,
          823.0
        ],
        [
          407.0,
          824.0
        ],
        [
          407.0,
          825.0
        ],
        [
          408.0,
          826.0
        ],
        [
          408.0,
          827.0
        ],
        [
          409.0,
          828.0
        ],
        [
          409.0,
          829.0
        ],
        [
          412.0,
          832.0
        ],
        [
          413.0,
          832.0
        ],
        [
          415.0,
          834.0
        ],
        [
          416.0,
          834.0
        ],
        [
          417.0,
          835.0
        ],
        [
          417.0,
          836.0
        ],
        [
          418.0,
          837.0
        ],
        [
          419.0,
          837.0
        ],
        [
          420.0,
          838.0
        ],
        [
          421.0,
          838.0
        ],
        [
          422.0,
          839.0
        ],
        [
          423.0,
          839.0
        ],
        [
          426.0,
          842.0
        ],
        [
          427.0,
          842.0
        ],
        [
          428.0,
          843.0
        ],
        [
          429.0,
          843.0
        ],
        [
          430.0,
          844.0
        ],
        [
          431.0,
          844.0
        ],
        [
          433.0,
          846.0
        ],
        [
          436.0,
          846.0
        ],
        [
          437.0,
          847.0
        ],
        [
          438.0,
          847.0
        ],
        [
          439.0,
          848.0
        ],
        [
          442.0,
          848.0
        ],
        [
          443.0,
          847.0
        ],
        [
          443.0,
          846.0
        ],
        [
          444.0,
          845.0
        ],
        [
          444.0,
          831.0
        ],
        [
          443.0,
          830.0
        ],
        [
          444.0,
          829.0
        ],
        [
          444.0,
          828.0
        ],
        [
          445.0,
          827.0
        ],
        [
          445.0,
          825.0
        ],
        [
          446.0,
          824.0
        ],
        [
          446.0,
          814.0
        ],
        [
          445.0,
          813.0
        ],
        [
          445.0,
          808.0
        ],
        [
          444.0,
          807.0
        ],
        [
          444.0,
          803.0
        ],
        [
          443.0,
          802.0
        ],
        [
          443.0,
          800.0
        ],
        [
          442.0,
          799.0
        ],
        [
          442.0,
          798.0
        ],
        [
          441.0,
          797.0
        ],
        [
          441.0,
          796.0
        ],
        [
          438.0,
          793.0
        ],
        [
          438.0,
          792.0
        ],
        [
          437.0,
          791.0
        ],
        [
          437.0,
          790.0
        ],
        [
          436.0,
          789.0
        ],
        [
          436.0,
          787.0
        ],
        [
          435.0,
          786.0
        ],
        [
          435.0,
          783.0
        ],
        [
          434.0,
          782.0
        ],
        [
          434.0,
          779.0
        ],
        [
          433.0,
          778.0
        ],
        [
          433.0,
          775.0
        ],
        [
          431.0,
          773.0
        ],
        [
          431.0,
          772.0
        ],
        [
          428.0,
          769.0
        ],
        [
          426.0,
          769.0
        ],
        [
          425.0,
          768.0
        ]
      ],
      "group_id": null,
      "description": null,
      "difficult": false,
      "shape_type": "polygon",
      "flags": null,
      "attributes": {},
      "kie_linking": []
    },
    {
      "label": "person",
      "score": 0.8443922996520996,
      "points": [
        [
          403.64642333984375,
          768.7741088867188
        ],
        [
          447.7366638183594,
          768.7741088867188
        ],
        [
          447.7366638183594,
          848.9674072265625
        ],
        [
          403.64642333984375,
          848.9674072265625
        ]
      ],
      "group_id": null,
      "description": null,
      "difficult": false,
      "shape_type": "rectangle",
      "flags": null,
      "attributes": {},
      "kie_linking": []
    }
  ],
  "imagePath": "frame_00002.jpg",
  "imageData": null,
  "imageHeight": 1920,
  "imageWidth": 1080,
  "description": ""
}